{"nodes": [{"id": "d_codes_socio_socioweb_client_app_catering_page_tsx", "label": "page.tsx", "file_type": "code", "source_file": "D:\\CODES\\SOCIO\\socioweb\\client\\app\\catering\\page.tsx", "source_location": "L1"}, {"id": "catering_page_safelower", "label": "safeLower()", "file_type": "code", "source_file": "D:\\CODES\\SOCIO\\socioweb\\client\\app\\catering\\page.tsx", "source_location": "L27"}, {"id": "catering_page_timeago", "label": "timeAgo()", "file_type": "code", "source_file": "D:\\CODES\\SOCIO\\socioweb\\client\\app\\catering\\page.tsx", "source_location": "L29"}, {"id": "catering_page_formatsubmitted", "label": "formatSubmitted()", "file_type": "code", "source_file": "D:\\CODES\\SOCIO\\socioweb\\client\\app\\catering\\page.tsx", "source_location": "L37"}, {"id": "catering_page_formateventdate", "label": "formatEventDate()", "file_type": "code", "source_file": "D:\\CODES\\SOCIO\\socioweb\\client\\app\\catering\\page.tsx", "source_location": "L43"}, {"id": "catering_page_formatmobilelist", "label": "formatMobileList()", "file_type": "code", "source_file": "D:\\CODES\\SOCIO\\socioweb\\client\\app\\catering\\page.tsx", "source_location": "L50"}, {"id": "catering_page_parsecontact", "label": "parseContact()", "file_type": "code", "source_file": "D:\\CODES\\SOCIO\\socioweb\\client\\app\\catering\\page.tsx", "source_location": "L56"}, {"id": "catering_page_statusbadge", "label": "StatusBadge()", "file_type": "code", "source_file": "D:\\CODES\\SOCIO\\socioweb\\client\\app\\catering\\page.tsx", "source_location": "L72"}, {"id": "catering_page_fetchbookings", "label": "fetchBookings()", "file_type": "code", "source_file": "D:\\CODES\\SOCIO\\socioweb\\client\\app\\catering\\page.tsx", "source_location": "L106"}, {"id": "catering_page_handleaction", "label": "handleAction()", "file_type": "code", "source_file": "D:\\CODES\\SOCIO\\socioweb\\client\\app\\catering\\page.tsx", "source_location": "L127"}], "edges": [{"source": "d_codes_socio_socioweb_client_app_catering_page_tsx", "target": "react", "relation": "imports_from", "context": "import", "confidence": "EXTRACTED", "source_file": "D:\\CODES\\SOCIO\\socioweb\\client\\app\\catering\\page.tsx", "source_location": "L3", "weight": 1.0}, {"source": "d_codes_socio_socioweb_client_app_catering_page_tsx", "target": "navigation", "relation": "imports_from", "context": "import", "confidence": "EXTRACTED", "source_file": "D:\\CODES\\SOCIO\\socioweb\\client\\app\\catering\\page.tsx", "source_location": "L4", "weight": 1.0}, {"source": "d_codes_socio_socioweb_client_app_catering_page_tsx", "target": "d_codes_socio_socioweb_client_context_authcontext", "relation": "imports_from", "context": "import", "confidence": "EXTRACTED", "source_file": "D:\\CODES\\SOCIO\\socioweb\\client\\app\\catering\\page.tsx", "source_location": "L5", "weight": 1.0}, {"source": "d_codes_socio_socioweb_client_app_catering_page_tsx", "target": "context_authcontext_useauth", "relation": "imports", "context": "import", "confidence": "EXTRACTED", "source_file": "D:\\CODES\\SOCIO\\socioweb\\client\\app\\catering\\page.tsx", "source_location": "L5", "weight": 1.0}, {"source": "d_codes_socio_socioweb_client_app_catering_page_tsx", "target": "react_hot_toast", "relation": "imports_from", "context": "import", "confidence": "EXTRACTED", "source_file": "D:\\CODES\\SOCIO\\socioweb\\client\\app\\catering\\page.tsx", "source_location": "L6", "weight": 1.0}, {"source": "d_codes_socio_socioweb_client_app_catering_page_tsx", "target": "catering_page_safelower", "relation": "contains", "confidence": "EXTRACTED", "source_file": "D:\\CODES\\SOCIO\\socioweb\\client\\app\\catering\\page.tsx", "source_location": "L27", "weight": 1.0}, {"source": "d_codes_socio_socioweb_client_app_catering_page_tsx", "target": "catering_page_timeago", "relation": "contains", "confidence": "EXTRACTED", "source_file": "D:\\CODES\\SOCIO\\socioweb\\client\\app\\catering\\page.tsx", "source_location": "L29", "weight": 1.0}, {"source": "d_codes_socio_socioweb_client_app_catering_page_tsx", "target": "catering_page_formatsubmitted", "relation": "contains", "confidence": "EXTRACTED", "source_file": "D:\\CODES\\SOCIO\\socioweb\\client\\app\\catering\\page.tsx", "source_location": "L37", "weight": 1.0}, {"source": "d_codes_socio_socioweb_client_app_catering_page_tsx", "target": "catering_page_formateventdate", "relation": "contains", "confidence": "EXTRACTED", "source_file": "D:\\CODES\\SOCIO\\socioweb\\client\\app\\catering\\page.tsx", "source_location": "L43", "weight": 1.0}, {"source": "d_codes_socio_socioweb_client_app_catering_page_tsx", "target": "catering_page_formatmobilelist", "relation": "contains", "confidence": "EXTRACTED", "source_file": "D:\\CODES\\SOCIO\\socioweb\\client\\app\\catering\\page.tsx", "source_location": "L50", "weight": 1.0}, {"source": "d_codes_socio_socioweb_client_app_catering_page_tsx", "target": "catering_page_parsecontact", "relation": "contains", "confidence": "EXTRACTED", "source_file": "D:\\CODES\\SOCIO\\socioweb\\client\\app\\catering\\page.tsx", "source_location": "L56", "weight": 1.0}, {"source": "d_codes_socio_socioweb_client_app_catering_page_tsx", "target": "catering_page_statusbadge", "relation": "contains", "confidence": "EXTRACTED", "source_file": "D:\\CODES\\SOCIO\\socioweb\\client\\app\\catering\\page.tsx", "source_location": "L72", "weight": 1.0}, {"source": "d_codes_socio_socioweb_client_app_catering_page_tsx", "target": "catering_page_fetchbookings", "relation": "contains", "confidence": "EXTRACTED", "source_file": "D:\\CODES\\SOCIO\\socioweb\\client\\app\\catering\\page.tsx", "source_location": "L106", "weight": 1.0}, {"source": "d_codes_socio_socioweb_client_app_catering_page_tsx", "target": "catering_page_handleaction", "relation": "contains", "confidence": "EXTRACTED", "source_file": "D:\\CODES\\SOCIO\\socioweb\\client\\app\\catering\\page.tsx", "source_location": "L127", "weight": 1.0}, {"source": "d_codes_socio_socioweb_client_app_catering_page_tsx", "target": "catering_page_timeago", "relation": "contains", "confidence": "EXTRACTED", "source_file": "D:\\CODES\\SOCIO\\socioweb\\client\\app\\catering\\page.tsx", "source_location": "L213", "weight": 1.0}, {"source": "catering_page_parsecontact", "target": "catering_page_formatmobilelist", "relation": "calls", "context": "call", "confidence": "EXTRACTED", "source_file": "D:\\CODES\\SOCIO\\socioweb\\client\\app\\catering\\page.tsx", "source_location": "L66", "weight": 1.0}], "raw_calls": [{"caller_nid": "catering_page_safelower", "callee": "toLowerCase", "is_member_call": true, "source_file": "D:\\CODES\\SOCIO\\socioweb\\client\\app\\catering\\page.tsx", "source_location": "L27"}, {"caller_nid": "catering_page_safelower", "callee": "String", "is_member_call": false, "source_file": "D:\\CODES\\SOCIO\\socioweb\\client\\app\\catering\\page.tsx", "source_location": "L27"}, {"caller_nid": "catering_page_timeago", "callee": "now", "is_member_call": true, "source_file": "D:\\CODES\\SOCIO\\socioweb\\client\\app\\catering\\page.tsx", "source_location": "L30"}, {"caller_nid": "catering_page_timeago", "callee": "getTime", "is_member_call": true, "source_file": "D:\\CODES\\SOCIO\\socioweb\\client\\app\\catering\\page.tsx", "source_location": "L30"}, {"caller_nid": "catering_page_timeago", "callee": "floor", "is_member_call": true, "source_file": "D:\\CODES\\SOCIO\\socioweb\\client\\app\\catering\\page.tsx", "source_location": "L31"}, {"caller_nid": "catering_page_formatsubmitted", "callee": "isNaN", "is_member_call": false, "source_file": "D:\\CODES\\SOCIO\\socioweb\\client\\app\\catering\\page.tsx", "source_location": "L39"}, {"caller_nid": "catering_page_formatsubmitted", "callee": "getTime", "is_member_call": true, "source_file": "D:\\CODES\\SOCIO\\socioweb\\client\\app\\catering\\page.tsx", "source_location": "L39"}, {"caller_nid": "catering_page_formatsubmitted", "callee": "toLocaleString", "is_member_call": true, "source_file": "D:\\CODES\\SOCIO\\socioweb\\client\\app\\catering\\page.tsx", "source_location": "L40"}, {"caller_nid": "catering_page_formateventdate", "callee": "isNaN", "is_member_call": false, "source_file": "D:\\CODES\\SOCIO\\socioweb\\client\\app\\catering\\page.tsx", "source_location": "L46"}, {"caller_nid": "catering_page_formateventdate", "callee": "getTime", "is_member_call": true, "source_file": "D:\\CODES\\SOCIO\\socioweb\\client\\app\\catering\\page.tsx", "source_location": "L46"}, {"caller_nid": "catering_page_formateventdate", "callee": "toLocaleDateString", "is_member_call": true, "source_file": "D:\\CODES\\SOCIO\\socioweb\\client\\app\\catering\\page.tsx", "source_location": "L47"}, {"caller_nid": "catering_page_formatmobilelist", "callee": "isArray", "is_member_call": true, "source_file": "D:\\CODES\\SOCIO\\socioweb\\client\\app\\catering\\page.tsx", "source_location": "L52"}, {"caller_nid": "catering_page_formatmobilelist", "callee": "join", "is_member_call": true, "source_file": "D:\\CODES\\SOCIO\\socioweb\\client\\app\\catering\\page.tsx", "source_location": "L52"}, {"caller_nid": "catering_page_formatmobilelist", "callee": "filter", "is_member_call": true, "source_file": "D:\\CODES\\SOCIO\\socioweb\\client\\app\\catering\\page.tsx", "source_location": "L52"}, {"caller_nid": "catering_page_formatmobilelist", "callee": "String", "is_member_call": false, "source_file": "D:\\CODES\\SOCIO\\socioweb\\client\\app\\catering\\page.tsx", "source_location": "L53"}, {"caller_nid": "catering_page_parsecontact", "callee": "parse", "is_member_call": true, "source_file": "D:\\CODES\\SOCIO\\socioweb\\client\\app\\catering\\page.tsx", "source_location": "L59"}, {"caller_nid": "catering_page_parsecontact", "callee": "isArray", "is_member_call": true, "source_file": "D:\\CODES\\SOCIO\\socioweb\\client\\app\\catering\\page.tsx", "source_location": "L61"}, {"caller_nid": "catering_page_statusbadge", "callee": "if", "is_member_call": false, "source_file": "D:\\CODES\\SOCIO\\socioweb\\client\\app\\catering\\page.tsx", "source_location": "L75"}, {"caller_nid": "catering_page_fetchbookings", "callee": "setLoading", "is_member_call": false, "source_file": "D:\\CODES\\SOCIO\\socioweb\\client\\app\\catering\\page.tsx", "source_location": "L107"}, {"caller_nid": "catering_page_fetchbookings", "callee": "fetch", "is_member_call": false, "source_file": "D:\\CODES\\SOCIO\\socioweb\\client\\app\\catering\\page.tsx", "source_location": "L109"}, {"caller_nid": "catering_page_fetchbookings", "callee": "catch", "is_member_call": true, "source_file": "D:\\CODES\\SOCIO\\socioweb\\client\\app\\catering\\page.tsx", "source_location": "L113"}, {"caller_nid": "catering_page_fetchbookings", "callee": "json", "is_member_call": true, "source_file": "D:\\CODES\\SOCIO\\socioweb\\client\\app\\catering\\page.tsx", "source_location": "L113"}, {"caller_nid": "catering_page_fetchbookings", "callee": "error", "is_member_call": true, "source_file": "D:\\CODES\\SOCIO\\socioweb\\client\\app\\catering\\page.tsx", "source_location": "L114"}, {"caller_nid": "catering_page_fetchbookings", "callee": "json", "is_member_call": true, "source_file": "D:\\CODES\\SOCIO\\socioweb\\client\\app\\catering\\page.tsx", "source_location": "L117"}, {"caller_nid": "catering_page_fetchbookings", "callee": "setVendors", "is_member_call": false, "source_file": "D:\\CODES\\SOCIO\\socioweb\\client\\app\\catering\\page.tsx", "source_location": "L118"}, {"caller_nid": "catering_page_fetchbookings", "callee": "setBookings", "is_member_call": false, "source_file": "D:\\CODES\\SOCIO\\socioweb\\client\\app\\catering\\page.tsx", "source_location": "L119"}, {"caller_nid": "catering_page_fetchbookings", "callee": "error", "is_member_call": true, "source_file": "D:\\CODES\\SOCIO\\socioweb\\client\\app\\catering\\page.tsx", "source_location": "L121"}, {"caller_nid": "catering_page_fetchbookings", "callee": "setLoading", "is_member_call": false, "source_file": "D:\\CODES\\SOCIO\\socioweb\\client\\app\\catering\\page.tsx", "source_location": "L123"}, {"caller_nid": "catering_page_handleaction", "callee": "setBookings", "is_member_call": false, "source_file": "D:\\CODES\\SOCIO\\socioweb\\client\\app\\catering\\page.tsx", "source_location": "L132"}, {"caller_nid": "catering_page_handleaction", "callee": "map", "is_member_call": true, "source_file": "D:\\CODES\\SOCIO\\socioweb\\client\\app\\catering\\page.tsx", "source_location": "L132"}, {"caller_nid": "catering_page_handleaction", "callee": "setActionBookingId", "is_member_call": false, "source_file": "D:\\CODES\\SOCIO\\socioweb\\client\\app\\catering\\page.tsx", "source_location": "L135"}, {"caller_nid": "catering_page_handleaction", "callee": "fetch", "is_member_call": false, "source_file": "D:\\CODES\\SOCIO\\socioweb\\client\\app\\catering\\page.tsx", "source_location": "L138"}, {"caller_nid": "catering_page_handleaction", "callee": "stringify", "is_member_call": true, "source_file": "D:\\CODES\\SOCIO\\socioweb\\client\\app\\catering\\page.tsx", "source_location": "L144"}, {"caller_nid": "catering_page_handleaction", "callee": "setBookings", "is_member_call": false, "source_file": "D:\\CODES\\SOCIO\\socioweb\\client\\app\\catering\\page.tsx", "source_location": "L148"}, {"caller_nid": "catering_page_handleaction", "callee": "catch", "is_member_call": true, "source_file": "D:\\CODES\\SOCIO\\socioweb\\client\\app\\catering\\page.tsx", "source_location": "L149"}, {"caller_nid": "catering_page_handleaction", "callee": "json", "is_member_call": true, "source_file": "D:\\CODES\\SOCIO\\socioweb\\client\\app\\catering\\page.tsx", "source_location": "L149"}, {"caller_nid": "catering_page_handleaction", "callee": "error", "is_member_call": true, "source_file": "D:\\CODES\\SOCIO\\socioweb\\client\\app\\catering\\page.tsx", "source_location": "L150"}, {"caller_nid": "catering_page_handleaction", "callee": "success", "is_member_call": true, "source_file": "D:\\CODES\\SOCIO\\socioweb\\client\\app\\catering\\page.tsx", "source_location": "L153"}, {"caller_nid": "catering_page_handleaction", "callee": "setBookings", "is_member_call": false, "source_file": "D:\\CODES\\SOCIO\\socioweb\\client\\app\\catering\\page.tsx", "source_location": "L156"}, {"caller_nid": "catering_page_handleaction", "callee": "error", "is_member_call": true, "source_file": "D:\\CODES\\SOCIO\\socioweb\\client\\app\\catering\\page.tsx", "source_location": "L157"}, {"caller_nid": "catering_page_handleaction", "callee": "setActionBookingId", "is_member_call": false, "source_file": "D:\\CODES\\SOCIO\\socioweb\\client\\app\\catering\\page.tsx", "source_location": "L159"}]}