{"nodes": [{"id": "d_codes_socio_socioweb_client_app_volunteer_scanner_eventid_page_tsx", "label": "page.tsx", "file_type": "code", "source_file": "D:\\CODES\\SOCIO\\socioweb\\client\\app\\volunteer\\scanner\\[eventId]\\page.tsx", "source_location": "L1"}, {"id": "eventid_page_normalizeregisternumber", "label": "normalizeRegisterNumber()", "file_type": "code", "source_file": "D:\\CODES\\SOCIO\\socioweb\\client\\app\\volunteer\\scanner\\[eventId]\\page.tsx", "source_location": "L17"}, {"id": "eventid_page_hasactivevolunteeraccess", "label": "hasActiveVolunteerAccess()", "file_type": "code", "source_file": "D:\\CODES\\SOCIO\\socioweb\\client\\app\\volunteer\\scanner\\[eventId]\\page.tsx", "source_location": "L20"}, {"id": "eventid_page_accessdenied", "label": "AccessDenied()", "file_type": "code", "source_file": "D:\\CODES\\SOCIO\\socioweb\\client\\app\\volunteer\\scanner\\[eventId]\\page.tsx", "source_location": "L36"}, {"id": "eventid_page_volunteerscannerpage", "label": "VolunteerScannerPage()", "file_type": "code", "source_file": "D:\\CODES\\SOCIO\\socioweb\\client\\app\\volunteer\\scanner\\[eventId]\\page.tsx", "source_location": "L52"}], "edges": [{"source": "d_codes_socio_socioweb_client_app_volunteer_scanner_eventid_page_tsx", "target": "react", "relation": "imports_from", "context": "import", "confidence": "EXTRACTED", "source_file": "D:\\CODES\\SOCIO\\socioweb\\client\\app\\volunteer\\scanner\\[eventId]\\page.tsx", "source_location": "L3", "weight": 1.0}, {"source": "d_codes_socio_socioweb_client_app_volunteer_scanner_eventid_page_tsx", "target": "navigation", "relation": "imports_from", "context": "import", "confidence": "EXTRACTED", "source_file": "D:\\CODES\\SOCIO\\socioweb\\client\\app\\volunteer\\scanner\\[eventId]\\page.tsx", "source_location": "L4", "weight": 1.0}, {"source": "d_codes_socio_socioweb_client_app_volunteer_scanner_eventid_page_tsx", "target": "lucide_react", "relation": "imports_from", "context": "import", "confidence": "EXTRACTED", "source_file": "D:\\CODES\\SOCIO\\socioweb\\client\\app\\volunteer\\scanner\\[eventId]\\page.tsx", "source_location": "L5", "weight": 1.0}, {"source": "d_codes_socio_socioweb_client_app_volunteer_scanner_eventid_page_tsx", "target": "d_codes_socio_socioweb_client_context_authcontext", "relation": "imports_from", "context": "import", "confidence": "EXTRACTED", "source_file": "D:\\CODES\\SOCIO\\socioweb\\client\\app\\volunteer\\scanner\\[eventId]\\page.tsx", "source_location": "L6", "weight": 1.0}, {"source": "d_codes_socio_socioweb_client_app_volunteer_scanner_eventid_page_tsx", "target": "context_authcontext_useauth", "relation": "imports", "context": "import", "confidence": "EXTRACTED", "source_file": "D:\\CODES\\SOCIO\\socioweb\\client\\app\\volunteer\\scanner\\[eventId]\\page.tsx", "source_location": "L6", "weight": 1.0}, {"source": "d_codes_socio_socioweb_client_app_volunteer_scanner_eventid_page_tsx", "target": "d_codes_socio_socioweb_client_lib_supabaseclient", "relation": "imports_from", "context": "import", "confidence": "EXTRACTED", "source_file": "D:\\CODES\\SOCIO\\socioweb\\client\\app\\volunteer\\scanner\\[eventId]\\page.tsx", "source_location": "L7", "weight": 1.0}, {"source": "d_codes_socio_socioweb_client_app_volunteer_scanner_eventid_page_tsx", "target": "lib_supabaseclient_supabase", "relation": "imports", "context": "import", "confidence": "EXTRACTED", "source_file": "D:\\CODES\\SOCIO\\socioweb\\client\\app\\volunteer\\scanner\\[eventId]\\page.tsx", "source_location": "L7", "weight": 1.0}, {"source": "d_codes_socio_socioweb_client_app_volunteer_scanner_eventid_page_tsx", "target": "d_codes_socio_socioweb_client_app_components_qrscanner", "relation": "imports_from", "context": "import", "confidence": "EXTRACTED", "source_file": "D:\\CODES\\SOCIO\\socioweb\\client\\app\\volunteer\\scanner\\[eventId]\\page.tsx", "source_location": "L8", "weight": 1.0}, {"source": "d_codes_socio_socioweb_client_app_volunteer_scanner_eventid_page_tsx", "target": "components_qrscanner_qrscanner", "relation": "imports", "context": "import", "confidence": "EXTRACTED", "source_file": "D:\\CODES\\SOCIO\\socioweb\\client\\app\\volunteer\\scanner\\[eventId]\\page.tsx", "source_location": "L8", "weight": 1.0}, {"source": "d_codes_socio_socioweb_client_app_volunteer_scanner_eventid_page_tsx", "target": "d_codes_socio_socioweb_client_app_components_ui_loadingindicator", "relation": "imports_from", "context": "import", "confidence": "EXTRACTED", "source_file": "D:\\CODES\\SOCIO\\socioweb\\client\\app\\volunteer\\scanner\\[eventId]\\page.tsx", "source_location": "L9", "weight": 1.0}, {"source": "d_codes_socio_socioweb_client_app_volunteer_scanner_eventid_page_tsx", "target": "eventid_page_normalizeregisternumber", "relation": "contains", "confidence": "EXTRACTED", "source_file": "D:\\CODES\\SOCIO\\socioweb\\client\\app\\volunteer\\scanner\\[eventId]\\page.tsx", "source_location": "L17", "weight": 1.0}, {"source": "d_codes_socio_socioweb_client_app_volunteer_scanner_eventid_page_tsx", "target": "eventid_page_hasactivevolunteeraccess", "relation": "contains", "confidence": "EXTRACTED", "source_file": "D:\\CODES\\SOCIO\\socioweb\\client\\app\\volunteer\\scanner\\[eventId]\\page.tsx", "source_location": "L20", "weight": 1.0}, {"source": "d_codes_socio_socioweb_client_app_volunteer_scanner_eventid_page_tsx", "target": "eventid_page_accessdenied", "relation": "contains", "confidence": "EXTRACTED", "source_file": "D:\\CODES\\SOCIO\\socioweb\\client\\app\\volunteer\\scanner\\[eventId]\\page.tsx", "source_location": "L36", "weight": 1.0}, {"source": "d_codes_socio_socioweb_client_app_volunteer_scanner_eventid_page_tsx", "target": "eventid_page_volunteerscannerpage", "relation": "contains", "confidence": "EXTRACTED", "source_file": "D:\\CODES\\SOCIO\\socioweb\\client\\app\\volunteer\\scanner\\[eventId]\\page.tsx", "source_location": "L52", "weight": 1.0}, {"source": "eventid_page_hasactivevolunteeraccess", "target": "eventid_page_normalizeregisternumber", "relation": "calls", "context": "call", "confidence": "EXTRACTED", "source_file": "D:\\CODES\\SOCIO\\socioweb\\client\\app\\volunteer\\scanner\\[eventId]\\page.tsx", "source_location": "L24", "weight": 1.0}], "raw_calls": [{"caller_nid": "eventid_page_normalizeregisternumber", "callee": "toUpperCase", "is_member_call": true, "source_file": "D:\\CODES\\SOCIO\\socioweb\\client\\app\\volunteer\\scanner\\[eventId]\\page.tsx", "source_location": "L18"}, {"caller_nid": "eventid_page_normalizeregisternumber", "callee": "trim", "is_member_call": true, "source_file": "D:\\CODES\\SOCIO\\socioweb\\client\\app\\volunteer\\scanner\\[eventId]\\page.tsx", "source_location": "L18"}, {"caller_nid": "eventid_page_normalizeregisternumber", "callee": "String", "is_member_call": false, "source_file": "D:\\CODES\\SOCIO\\socioweb\\client\\app\\volunteer\\scanner\\[eventId]\\page.tsx", "source_location": "L18"}, {"caller_nid": "eventid_page_hasactivevolunteeraccess", "callee": "isArray", "is_member_call": true, "source_file": "D:\\CODES\\SOCIO\\socioweb\\client\\app\\volunteer\\scanner\\[eventId]\\page.tsx", "source_location": "L25"}, {"caller_nid": "eventid_page_hasactivevolunteeraccess", "callee": "some", "is_member_call": true, "source_file": "D:\\CODES\\SOCIO\\socioweb\\client\\app\\volunteer\\scanner\\[eventId]\\page.tsx", "source_location": "L27"}, {"caller_nid": "eventid_page_volunteerscannerpage", "callee": "useParams", "is_member_call": false, "source_file": "D:\\CODES\\SOCIO\\socioweb\\client\\app\\volunteer\\scanner\\[eventId]\\page.tsx", "source_location": "L53"}, {"caller_nid": "eventid_page_volunteerscannerpage", "callee": "String", "is_member_call": false, "source_file": "D:\\CODES\\SOCIO\\socioweb\\client\\app\\volunteer\\scanner\\[eventId]\\page.tsx", "source_location": "L54"}, {"caller_nid": "eventid_page_volunteerscannerpage", "callee": "useAuth", "is_member_call": false, "source_file": "D:\\CODES\\SOCIO\\socioweb\\client\\app\\volunteer\\scanner\\[eventId]\\page.tsx", "source_location": "L55"}, {"caller_nid": "eventid_page_volunteerscannerpage", "callee": "useState", "is_member_call": false, "source_file": "D:\\CODES\\SOCIO\\socioweb\\client\\app\\volunteer\\scanner\\[eventId]\\page.tsx", "source_location": "L56"}, {"caller_nid": "eventid_page_volunteerscannerpage", "callee": "useState", "is_member_call": false, "source_file": "D:\\CODES\\SOCIO\\socioweb\\client\\app\\volunteer\\scanner\\[eventId]\\page.tsx", "source_location": "L57"}, {"caller_nid": "eventid_page_volunteerscannerpage", "callee": "useState", "is_member_call": false, "source_file": "D:\\CODES\\SOCIO\\socioweb\\client\\app\\volunteer\\scanner\\[eventId]\\page.tsx", "source_location": "L58"}, {"caller_nid": "eventid_page_volunteerscannerpage", "callee": "useEffect", "is_member_call": false, "source_file": "D:\\CODES\\SOCIO\\socioweb\\client\\app\\volunteer\\scanner\\[eventId]\\page.tsx", "source_location": "L60"}]}